stepversion/StepVersion.py
stepversion/__init__.py
stepversion/_version.py
stepversion-0.9.1.dist-info/LICENSE
stepversion-0.9.1.dist-info/METADATA
stepversion-0.9.1.dist-info/WHEEL
stepversion-0.9.1.dist-info/entry_points.txt
stepversion-0.9.1.dist-info/top_level.txt
stepversion-0.9.1.dist-info/RECORD
