Metadata-Version: 2.1
Name: stepversion
Version: 0.9.1
Summary: Bump package versions
Home-page: https://github.com/hasii2011/stepversion
Author: Humberto A. Sanchez II
Author-email: humberto.a.sanchez.ii@gmail.com
Maintainer: Humberto A. Sanchez II
Maintainer-email: humberto.a.sanchez.ii@gmail.com
License: GNU AFFERO GENERAL PUBLIC LICENSE
License-File: LICENSE
Requires-Dist: click ==8.1.7
